pytorch_caney/__init__.py
pytorch_caney/config.py
pytorch_caney/inference.py
pytorch_caney/lr_scheduler.py
pytorch_caney/metrics.py
pytorch_caney/processing.py
pytorch_caney/ptc_logging.py
pytorch_caney/utils.py
pytorch_caney/console/__init__.py
pytorch_caney/console/cli.py
pytorch_caney/console/dl_pipeline.py
pytorch_caney/models/__init__.py
pytorch_caney/models/build.py
pytorch_caney/models/maskrcnn_model.py
pytorch_caney/models/swinv2_model.py
pytorch_caney/models/unet_model.py
pytorch_caney/models/unet_swin_model.py
pytorch_caney/models/mim/__init__.py
pytorch_caney/models/mim/mim.py
pytorch_caney/models/simmim/__init__.py
pytorch_caney/models/simmim/simmim.py
pytorch_caney/network/__init__.py
pytorch_caney/network/attention.py
pytorch_caney/network/mlp.py
pytorch_caney-0.1.0.dist-info/LICENSE.md
pytorch_caney-0.1.0.dist-info/METADATA
pytorch_caney-0.1.0.dist-info/WHEEL
pytorch_caney-0.1.0.dist-info/top_level.txt
pytorch_caney-0.1.0.dist-info/zip-safe
pytorch_caney-0.1.0.dist-info/RECORD
