Metadata-Version: 2.1
Name: pytorch-caney
Version: 0.1.0
Summary: Methods for pytorch deep learning applications
Home-page: https://github.com/nasa-nccs-hpda/pytorch-caney
Author: jordancaraballo
Author-email: jordan.a.caraballo-vega@nasa.gov
License: MIT
Project-URL: Documentation, https://github.com/nasa-nccs-hpda/pytorch-caney
Project-URL: Source, https://github.com/nasa-nccs-hpda/pytorch-caney
Project-URL: Issues, https://github.com/nasa-nccs-hpda/pytorch-caney/issues
Keywords: pytorch-caney,deep-learning,machine-learning
Classifier: Development Status :: 4 - Beta
Classifier: Intended Audience :: Developers
Classifier: Intended Audience :: Science/Research
Classifier: Topic :: Software Development :: Libraries :: Python Modules
Classifier: License :: OSI Approved :: MIT License
Classifier: Programming Language :: Python :: 3 :: Only
Requires-Python: >=3.7
License-File: LICENSE.md
Requires-Dist: omegaconf
Requires-Dist: numpy
Requires-Dist: pandas
Requires-Dist: tqdm
Requires-Dist: xarray
Requires-Dist: rioxarray
Requires-Dist: numba
Provides-Extra: all
Requires-Dist: pdoc ==8.0.1 ; extra == 'all'
Requires-Dist: pytest ; extra == 'all'
Requires-Dist: coverage[toml] ; extra == 'all'
Requires-Dist: black ; extra == 'all'
Provides-Extra: docs
Requires-Dist: pdoc ==8.0.1 ; extra == 'docs'
Provides-Extra: test
Requires-Dist: pytest ; extra == 'test'
Requires-Dist: coverage[toml] ; extra == 'test'
Requires-Dist: black ; extra == 'test'
